Metadata-Version: 2.1
Name: content-extractor-pi
Version: 0.0.8
Summary: Content extractor for files containing text
Home-page: https://gitlab.com/qarik/data-science/gcp_docunderstanding_spike/-/tree/content_extractor
Author: Paolo Italiani
Author-email: paoita@hotmail.it
License: MIT
Platform: UNKNOWN
License-File: LICENSE.txt
